[
    {
        "name": "Rajasthan Forest Department Calendar 2025",
        "date_of_notification": "2025-02-24",
        "date_of_commencement": "",
        "end_date": "",
        "apply_link": "https://forest.rajasthan.gov.in/content/dam/raj/forest/ForestDepartment/PDFs/calendar/Calendar%202025.pdf",
        "event_type": "Exam",
        "document_links": [
            "https://forest.rajasthan.gov.in/content/dam/raj/forest/ForestDepartment/PDFs/calendar/Calendar%202025.pdf",
            "https://forest.rajasthan.gov.in/content/raj/forest/en/home.html#"
        ]
    }
]