[
    {
        "name": "UPSC Exams",
        "date_of_notification": "2025-02-24",
        "date_of_commencement": "",
        "end_date": "",
        "apply_link": "https://upsc.gov.in/examinations/Indian%20Forest%20Service%20%28Preliminary%29%20Examination%2C%202024%20through%20CS%28P%29%20Examination%202024",
        "event_type": "Exam",
        "document_links": [
            "https://upsc.gov.in/sites/default/files/Notif-IFSP-24-engl-140224.pdf"
        ],
        "details": {
            "Exam": {
                "Event Type": "Exam",
                "Apply Link": "https://upsc.gov.in/examinations/Indian%20Forest%20Service%20%28Preliminary%29%20Examination%2C%202024%20through%20CS%28P%29%20Examination%202024"
            }
        }
    },
    {
        "name": "Indian Forest Service Preliminary Examination, 2024",
        "date_of_notification": "24-02-2025",
        "date_of_commencement": "",
        "end_date": "01-07-2024",
        "apply_link": "https://upsc.gov.in/examinations/Indian%20Forest%20Service%20%28Preliminary%29%20Examination%2C%202024%20through%20CS%28P%29%20Examination%202024",
        "event_type": "Exam",
        "document_links": [
            "https://upsc.gov.in/sites/default/files/IFoSP_2024_WR_Eng_01072024.pdf"
        ]
    }
]