[
    {
        "name": "Written Examination (CBRE) Result",
        "date_of_notification": "2025-02-24",
        "date_of_commencement": "2024-12-07",
        "end_date": "2024-12-18",
        "apply_link": "https://odishapolice.gov.in/main/sites/default/files/PDF/Notice No. 12_SSB, Dt. 01.02.2025_0.pdf",
        "event_type": "Exam",
        "document_links": [
            "https://odishapolice.gov.in"
        ],
        "details": {
            "additional_details": "Provisional results of the written examination (CBRE) held from 07.12.2024 to 18.12.2024 for the post of Sepoys/ Constables in OSAP / IR / SS Battalions are hereby published."
        }
    },
    {
        "name": "Final Answer Keys of Computer Based Recruitment Examination (CBRE) for the post of Driver in PMT Establishment",
        "date_of_notification": "2025-02-24",
        "date_of_commencement": "2025-01-20",
        "end_date": "2025-01-22",
        "apply_link": "https://opdriver.cbexams.com",
        "event_type": "Exam",
        "document_links": [
            "https://odishapolice.gov.in/main/sites/default/files/PDF/Notice No. 203_Estt., Dt. 18.01.2025.pdf",
            "https://odishapolice.gov.in"
        ],
        "details": {
            "Issued By": "Amitabh Thakur, IPS, ADGP, Transport Commissioner -cum- Chairman, Recruitment of Drivers in P,M,T Odisha, Cuttack,"
        }
    }
]